fleetcomp/__init__.py
fleetcomp/admin.py
fleetcomp/app_settings.py
fleetcomp/apps.py
fleetcomp/auth_hooks.py
fleetcomp/esi.py
fleetcomp/managers.py
fleetcomp/models.py
fleetcomp/tasks.py
fleetcomp/urls.py
fleetcomp/views.py
fleetcomp/locale/en/LC_MESSAGES/django.mo
fleetcomp/locale/en/LC_MESSAGES/django.po
fleetcomp/management/commands/populate_default_groupings.py
fleetcomp/migrations/0001_initial.py
fleetcomp/migrations/0002_rename_customgrouping_shipgrouping.py
fleetcomp/migrations/__init__.py
fleetcomp/templates/fleetcomp/all_fleet_commanders.html
fleetcomp/templates/fleetcomp/base.html
fleetcomp/templates/fleetcomp/index.html
fleetcomp/templates/fleetcomp/snapshot.html
fleetcomp/templates/fleetcomp/modals/base.html
fleetcomp/templates/fleetcomp/modals/content_base.html
fleetcomp/templates/fleetcomp/modals/loader_body.html
fleetcomp/templates/fleetcomp/modals/user_details.html
fleetcomp/templates/fleetcomp/overrides/top-menu-rh-fleetcomp.html
fleetcomp/templates/fleetcomp/partials/handle_modals.html
fleetcomp/templates/fleetcomp/partials/left_header.html
fleetcomp/templates/fleetcomp/partials/right_header.html
fleetcomp/templates/fleetcomp/partials/user_details.html
fleetcomp/templatetags/__init__.py
fleetcomp/templatetags/fleetcomp.py
fleetcomp/tests/__init__.py
fleetcomp/tests/test_managers.py
fleetcomp/tests/test_snapshot.py
fleetcomp/tests/test_tasks.py
fleetcomp/tests/testdata/README.md
fleetcomp/tests/testdata/__init__.py
fleetcomp/tests/testdata/create_eveuniverse.py
fleetcomp/tests/testdata/eveuniverse.json
fleetcomp/tests/testdata/load_eveuniverse.py
aa_fleetcomp-1.2.4.dist-info/licenses/LICENSE
aa_fleetcomp-1.2.4.dist-info/WHEEL
aa_fleetcomp-1.2.4.dist-info/METADATA
aa_fleetcomp-1.2.4.dist-info/RECORD
