Metadata-Version: 2.4
Name: aa-fleetcomp
Version: 1.2.4
Summary: Fleet composition analyzer for Alliance Auth
Author-email: T'rahk Rokym <trahk.rokym@gmail.com>
Requires-Python: >=3.10
Classifier: Environment :: Web Environment
Classifier: Framework :: Django
Classifier: Framework :: Django :: 4.2
Classifier: Intended Audience :: Developers
Classifier: License :: OSI Approved :: MIT License
Classifier: Operating System :: OS Independent
Classifier: Programming Language :: Python
Classifier: Programming Language :: Python :: 3.10
Classifier: Programming Language :: Python :: 3.11
Classifier: Programming Language :: Python :: 3.12
Classifier: Topic :: Internet :: WWW/HTTP
Classifier: Topic :: Internet :: WWW/HTTP :: Dynamic Content
License-File: LICENSE
Requires-Dist: allianceauth>=4
Requires-Dist: django-eveuniverse>=1.5
Project-URL: Changelog, https://gitlab.com/r0kym/aa-fleetcomp/-/blob/master/CHANGELOG.md
Project-URL: Homepage, https://gitlab.com/r0kym/aa-fleetcomp
Project-URL: Source, https://gitlab.com/r0kym/aa-fleetcomp
Project-URL: Tracker, https://gitlab.com/r0kym/aa-fleetcomp/-/issues
